funcnodes_keras/__init__.py
funcnodes_keras/applications.py
funcnodes_keras/callbacks.py
funcnodes_keras/datasets.py
funcnodes_keras/fit.py
funcnodes_keras/layers.py
funcnodes_keras/losses.py
funcnodes_keras/metrics.py
funcnodes_keras/models.py
funcnodes_keras/optimizers.py
funcnodes_keras/utilities.py
funcnodes_keras-0.1.14.dist-info/METADATA
funcnodes_keras-0.1.14.dist-info/WHEEL
funcnodes_keras-0.1.14.dist-info/entry_points.txt
funcnodes_keras-0.1.14.dist-info/RECORD
